eia/__init__.py
eia/api/__init__.py
eia/api/base.py
eia/api/category.py
eia/api/geoset.py
eia/api/relation.py
eia/api/search.py
eia/api/series.py
eia/api/series_category.py
eia/api/updates.py
eia/browser.py
eia/constants.py
eia/settings.py
pyeia-0.1.6.dist-info/WHEEL
pyeia-0.1.6.dist-info/METADATA
pyeia-0.1.6.dist-info/RECORD
